{"id":"JxHc","dependencies":[{"name":"/mnt/c/Users/taylo/Ethereum/web3data-js/node_modules/core-js/package.json","includedInParent":true,"mtime":1536617693151},{"name":"/mnt/c/Users/taylo/Ethereum/web3data-js/package.json","includedInParent":true,"mtime":1536641863786},{"name":"/mnt/c/Users/taylo/Ethereum/web3data-js/.babelrc","includedInParent":true,"mtime":1536616075155},{"name":"./_export","loc":{"line":2,"column":22},"parent":"/mnt/c/Users/taylo/Ethereum/web3data-js/node_modules/core-js/modules/es6.number.max-safe-integer.js","resolved":"/mnt/c/Users/taylo/Ethereum/web3data-js/node_modules/core-js/modules/_export.js"}],"generated":{"js":"var r=require(\"./_export\");r(r.S,\"Number\",{MAX_SAFE_INTEGER:9007199254740991});","map":{"mappings":[{"source":"node_modules/core-js/modules/es6.number.max-safe-integer.js","original":{"line":2,"column":0},"generated":{"line":1,"column":0}},{"source":"node_modules/core-js/modules/es6.number.max-safe-integer.js","original":{"line":2,"column":0},"generated":{"line":1,"column":4}},{"source":"node_modules/core-js/modules/es6.number.max-safe-integer.js","original":{"line":2,"column":0},"generated":{"line":1,"column":6}},{"source":"node_modules/core-js/modules/es6.number.max-safe-integer.js","original":{"line":2,"column":0},"generated":{"line":1,"column":14}},{"source":"node_modules/core-js/modules/es6.number.max-safe-integer.js","original":{"line":4,"column":0},"generated":{"line":1,"column":27}},{"source":"node_modules/core-js/modules/es6.number.max-safe-integer.js","original":{"line":4,"column":0},"generated":{"line":1,"column":29}},{"source":"node_modules/core-js/modules/es6.number.max-safe-integer.js","original":{"line":4,"column":0},"generated":{"line":1,"column":31}},{"source":"node_modules/core-js/modules/es6.number.max-safe-integer.js","original":{"line":4,"column":0},"generated":{"line":1,"column":33}},{"source":"node_modules/core-js/modules/es6.number.max-safe-integer.js","original":{"line":4,"column":0},"generated":{"line":1,"column":42}},{"source":"node_modules/core-js/modules/es6.number.max-safe-integer.js","original":{"line":4,"column":0},"generated":{"line":1,"column":43}},{"source":"node_modules/core-js/modules/es6.number.max-safe-integer.js","original":{"line":4,"column":0},"generated":{"line":1,"column":60}}],"sources":{"node_modules/core-js/modules/es6.number.max-safe-integer.js":"// 20.1.2.6 Number.MAX_SAFE_INTEGER\nvar $export = require('./_export');\n\n$export($export.S, 'Number', { MAX_SAFE_INTEGER: 0x1fffffffffffff });\n"},"lineCount":null}},"hash":"82f37552da31afdfea1a49cd3d482312","cacheData":{"env":{}}}